{
    "id": "2c39eebc-6e94-4aab-85f6-e3e4315faa31",
    "version": {
        "major": 0,
        "minor": 50,
        "patch": 7,
        "extra": ""
    },
    "xpCost": 155,
    "source": "Era Report 3052",
    "name": "Comstar - Federated Commonwealth Alliance (Steiner)",
    "flavorText": "I was raised in the culture of ComStar—taught that knowledge is power, silence is sacred, and to guard humanity is to hold its secrets.",
    "age": 0,
    "xpDiscount": 0,
    "minimumYear": 3030,
    "maximumYear": 3052,
    "randomWeight": 1.0,
    "lifeStages": [
        "AFFILIATION"
    ],
    "categories": [
        "GENERAL_INNER_SPHERE"
    ],
    "isPlayerRestricted": false,
    "requirementsFactions": {
        "0": [
            "CS"
        ]
    },
    "requirementsLifePath": {
        "0": []
    },
    "requirementsCategories": {
        "0": {}
    },
    "requirementsAttributes": {
        "0": {}
    },
    "requirementsTraits": {
        "0": {}
    },
    "requirementsSkills": {
        "0": {}
    },
    "requirementsAbilities": {
        "0": {}
    },
    "exclusionsFactions": {
        "0": []
    },
    "exclusionsLifePath": {
        "0": []
    },
    "exclusionsCategories": {
        "0": {}
    },
    "exclusionsAttributes": {
        "0": {}
    },
    "exclusionsTraits": {
        "0": {}
    },
    "exclusionsSkills": {
        "0": {}
    },
    "exclusionsAbilities": {
        "0": {}
    },
    "fixedXPAttributes": {
        "0": {
            "INTELLIGENCE": 25,
            "WILLPOWER": 50,
            "CHARISMA": -100
        }
    },
    "fixedXPTraits": {
        "0": {
            "CONNECTIONS": 100,
            "REPUTATION": 50
        }
    },
    "fixedXPSkills": {
        "0": {
            "Negotiation": 10,
            "Language/Any (RP Only)": 15,
            "Communications/Any (RP Only)": 10,
            "Interest/History (RP Only)": 25,
            "Protocols/Any (RP Only)": 20
        }
    },
    "fixedXPAbilities": {
        "0": {
            "flaw_introvert": -50
        }
    },
    "flexibleXPAttributes": {
        "0": {},
        "1": {},
        "2": {},
        "3": {},
        "4": {},
        "5": {},
        "6": {},
        "7": {},
        "8": {},
        "9": {},
        "10": {},
        "11": {}
    },
    "flexibleXPTraits": {
        "0": {},
        "1": {},
        "2": {},
        "3": {},
        "4": {},
        "5": {},
        "6": {},
        "7": {},
        "8": {},
        "9": {},
        "10": {},
        "11": {}
    },
    "flexibleXPSkills": {
        "0": {
            "Tech/Aero": 5
        },
        "1": {
            "Tech/BattleArmor": 5
        },
        "2": {
            "Tech/Mechanic": 5
        },
        "3": {
            "Tech/Mek": 5
        },
        "4": {
            "Tech/Vessel": 5
        },
        "5": {
            "Astech": 5
        },
        "6": {
            "Tech/Aero": 5
        },
        "7": {
            "Tech/BattleArmor": 5
        },
        "8": {
            "Tech/Mechanic": 5
        },
        "9": {
            "Tech/Mek": 5
        },
        "10": {
            "Tech/Vessel": 5
        },
        "11": {
            "Astech": 5
        }
    },
    "flexibleXPAbilities": {
        "0": {
            "atow_combat_paralysis": -100
        },
        "1": {
            "atow_combat_paralysis": -100
        },
        "2": {
            "atow_combat_paralysis": -100
        },
        "3": {
            "atow_combat_paralysis": -100
        },
        "4": {
            "atow_combat_paralysis": -100
        },
        "5": {
            "atow_combat_paralysis": -100
        },
        "6": {
            "flaw_glass_jaw": -100
        },
        "7": {
            "flaw_glass_jaw": -100
        },
        "8": {
            "flaw_glass_jaw": -100
        },
        "9": {
            "flaw_glass_jaw": -100
        },
        "10": {
            "flaw_glass_jaw": -100
        },
        "11": {
            "flaw_glass_jaw": -100
        }
    },
    "flexibleXPPickCount": 1
}
